buildgen/__init__.py
buildgen/generator.py
buildgen/makefile_generator.py
buildgen/ninja_generator.py
buildgen/writer.py
dragon/__init__.py
dragon/device.py
dragon/editor.py
dragon/lo.py
dragon/prebuild.py
dragon/test.py
dragon/update_check.py
dragon/util.py
dragon/wizard.py
dragon/config/banner.txt
dragon/config/defaults.yml
dragon/config/rules.yml
dragon/config/state.yml
dragon/config/targets.yml
dragon/config/tests.yml
dragon/config/types.yml
dragon/shscripts/building
dragon/shscripts/dragoncolors
dragon/shscripts/generator
dragon/shscripts/packaging
dragon/shscripts/prerun_checks
dragon/shscripts/remote
dragon/shscripts/simulator
dragon/shscripts/upgrader
dragon/shscripts/util
dragon/shscripts/variables
dragon-2.0.0.data/scripts/dragon
dragongen/__init__.py
dragongen/bfilter.py
dragongen/cliutils.py
dragongen/control.py
dragongen/generation.py
dragongen/theos.py
dragongen/toolchain.py
dragongen/util.py
dragongen/variable_types.py
shared/util.py
dragon-2.0.0.dist-info/LICENSE
dragon-2.0.0.dist-info/METADATA
dragon-2.0.0.dist-info/WHEEL
dragon-2.0.0.dist-info/top_level.txt
dragon-2.0.0.dist-info/RECORD
