Metadata-Version: 2.1
Name: dragon
Version: 2.0.0
Summary: A powerful toolkit targeting Apple development, research, and packaging.
Home-page: https://dragon.cynder.me/
Author: cynder
License-File: LICENSE
Requires-Dist: ninja
Requires-Dist: pyyaml
Requires-Dist: ruyaml
Requires-Dist: packaging
Requires-Dist: tqdm
